docs/conf.py
kaleidoscope/__init__.py
kaleidoscope/errors.py
kaleidoscope/version.py
kaleidoscope/colors/__init__.py
kaleidoscope/colors/cmap.py
kaleidoscope/colors/utils.py
kaleidoscope/interactive/__init__.py
kaleidoscope/interactive/histogram.py
kaleidoscope/interactive/plotly_wrapper.py
kaleidoscope/interactive/qsphere.py
kaleidoscope/interactive/bloch/__init__.py
kaleidoscope/interactive/bloch/bloch2d.py
kaleidoscope/interactive/bloch/bloch3d.py
kaleidoscope/interactive/bloch/primitives.py
kaleidoscope/interactive/bloch/utils.py
kaleidoscope/qiskit/__init__.py
kaleidoscope/qiskit/backends/__init__.py
kaleidoscope/qiskit/backends/device_layouts.py
kaleidoscope/qiskit/backends/layouts.json
kaleidoscope/qiskit/backends/pseudobackend.py
kaleidoscope/qiskit/backends/interactive/__init__.py
kaleidoscope/qiskit/backends/interactive/error_map.py
kaleidoscope/qiskit/backends/interactive/gate_map.py
kaleidoscope/qiskit/backends/mpl/__init__.py
kaleidoscope/qiskit/backends/mpl/cnot_err.py
kaleidoscope/test/__init__.py
kaleidoscope/test/no_qiskit/__init__.py
kaleidoscope/test/no_qiskit/test_bloch.py
kaleidoscope/test/qiskit/__init__.py
kaleidoscope/test/qiskit/test_qsphere.py
kaleidoscope/test/qiskit/test_target_backend.py
kaleidoscope/utils/__init__.py
kaleidoscope/utils/hardware.py
kaleidoscope/utils/pi_check.py
kaleidoscope-0.2.0.dist-info/LICENSE
kaleidoscope-0.2.0.dist-info/METADATA
kaleidoscope-0.2.0.dist-info/WHEEL
kaleidoscope-0.2.0.dist-info/top_level.txt
kaleidoscope-0.2.0.dist-info/RECORD
